[
    {
        "pregunta": "¿Cuál es el ingrediente principal en la receta clásica de la salsa pesto?",
        "respuesta_correcta": "Albahaca",
        "opciones_respuesta": [
            "Tomate",
            "Albahaca",
            "Espinaca",
            "Perejil"
        ],
        "img": "https://i.blogs.es/8fd947/salsa-pesto/840_560.jpg"
    },
    {
        "pregunta": "¿Qué tipo de queso se usa tradicionalmente en la elaboración de la auténtica fondue suiza?",
        "respuesta_correcta": "Emmental",
        "opciones_respuesta": [
            "Gouda",
            "Emmental",
            "Cheddar",
            "Brie"
        ],
        "img": "https://upload.wikimedia.org/wikipedia/commons/5/5f/Swiss_fondue_2.jpg"
    },
    {
        "pregunta": "¿Qué tipo de carne se utiliza para hacer el plato italiano ossobuco?",
        "respuesta_correcta": "Ternera",
        "opciones_respuesta": [
            "Cerdo",
            "Ternera",
            "Cordero",
            "Pollo"
        ],
        "img": "https://imag.bonviveur.com/osobuco-al-vino-tinto.jpg"
    },
    {
        "pregunta": "¿Qué ingrediente es esencial en la elaboración del ceviche, un plato típico de varios países latinoamericanos?",
        "respuesta_correcta": "Limón",
        "opciones_respuesta": [
            "Limón",
            "Coco",
            "Vinagre",
            "Tomate"
        ], "img": "https://img2.rtve.es/v/3491534?w=1600&preview=1455805214758.png"
    },
    {
        "pregunta": "¿Cuál es el principal componente del hummus, un plato popular en la cocina del Medio Oriente?",
        "respuesta_correcta": "Garbanzos",
        "opciones_respuesta": [
            "Garbanzos",
            "Lentejas",
            "Alubias",
            "Guisantes"
        ], "img": "https://www.piloncilloyvainilla.com/wp-content/uploads/2023/06/hummua-rwecipe-13-500x500.jpg"
    },
    {
        "pregunta": "¿Qué nombre recibe el plato peruano compuesto por pescado crudo marinado en limón?",
        "respuesta_correcta": "Ceviche",
        "opciones_respuesta": [
            "Arepa",
            "Causa",
            "Lomo saltado",
            "Ceviche"
        ], "img": "https://upload.wikimedia.org/wikipedia/commons/thumb/c/cf/Flag_of_Peru.svg/1200px-Flag_of_Peru.svg.png"
    },
    {
        "pregunta": "¿Cuál es el ingrediente principal en la receta tradicional de la paella española?",
        "respuesta_correcta": "Arroz",
        "opciones_respuesta": [
            "Pollo",
            "Gambas",
            "Arroz",
            "Cerdo"
        ], "img": "https://www.teleadhesivo.com/es/img/cou80-jpg/folder/products-listado-merchant/pegatinas-coches-motos-bandera-valencia.jpg"
    },
    {
        "pregunta": "¿Qué tipo de queso se utiliza comúnmente en la preparación de la auténtica pizza margarita italiana?",
        "respuesta_correcta": "Mozzarella",
        "opciones_respuesta": [
            "Mozzarella",
            "Gorgonzola",
            "Parmesano",
            "Ricotta"
        ], "img": "https://resizer.glanacion.com/resizer/v2/la-pizza-margarita-lleva-los-colores-de-la-M7NX62ONAJGRHMGZQKL3UMOIG4.jpeg?auth=95a4f0c18b4249f8a85c43e89ed95fc56dbfa22ac852945962285bb3c2638680&width=768&height=512&quality=70&smart=true"
    },
    {
        "pregunta": "¿Qué fruta se utiliza para hacer el plato mexicano de guacamole?",
        "respuesta_correcta": "Aguacate",
        "opciones_respuesta": [
            "Mango",
            "Aguacate",
            "Papaya",
            "Piña"
        ], "img": "https://www.giallozafferano.com/images/255-25549/Guacamole_1200x800.jpg"
    },
    {
        "pregunta": "¿Cuál es el ingrediente clave en la preparación del famoso plato francés ratatouille?",
        "respuesta_correcta": "Hortalizas",
        "opciones_respuesta": [
            "Carnes",
            "Pescados",
            "Hortalizas",
            "Caramelo"
        ], "img": "https://www.latercera.com/resizer/LifqY0LxdStFJm87Qd7eNUyGHqE=/900x600/filters:focal(281x243:291x233)/cloudfront-us-east-1.images.arcpublishing.com/copesa/D4NDZ2VDHRGCPNJ3SX6XFDKIRQ.jpg"
    },
    {
        "pregunta": "¿Qué ingrediente se usa comúnmente para hacer la salsa tzatziki griega?",
        "respuesta_correcta": "Yogur",
        "opciones_respuesta": [
            "Yogur",
            "Crema agria",
            "Mayonesa",
            "Salsa de tomate"
        ], "img": "https://lacosmopolilla.com/wp-content/uploads/2022/03/Es-seguro-viajar-a-Grecia-mi-experiencia-e1647451072255.jpg"
    },
    {
        "pregunta": "¿Cuál es el nombre del plato de pasta italiano que significa 'pequeños cascos'?",
        "respuesta_correcta": "Conchiglie",
        "opciones_respuesta": [
            "Farfalle",
            "Penne",
            "Conchiglie",
            "Fusilli"
        ], "img": "https://debandera.es/248-large_default/bandera-de-italia.jpg"
    },
    {
        "pregunta": "¿Qué tipo de alga marina se utiliza para envolver sushi japonés tradicional?",
        "respuesta_correcta": "Nori",
        "opciones_respuesta": [
            "Nori",
            "Wakame",
            "Kombu",
            "Hijiki"
        ], "img": "https://mejorconsalud.as.com/wp-content/uploads/2020/09/algas-nori.jpg"
    },
    {
        "pregunta": "¿Qué ingrediente es esencial en la receta del plato griego moussaka?",
        "respuesta_correcta": "Berenjena",
        "opciones_respuesta": [
            "Berenjena",
            "Lentejas",
            "Pepino",
            "Pimiento"
        ], "img": "https://lacosmopolilla.com/wp-content/uploads/2022/03/Es-seguro-viajar-a-Grecia-mi-experiencia-e1647451072255.jpg"
    },
    {
        "pregunta": "¿Qué tipo de queso se usa tradicionalmente en el plato suizo raclette?",
        "respuesta_correcta": "Emmental",
        "opciones_respuesta": [
            "Gouda",
            "Emmental",
            "Cheddar",
            "Feta"
        ], "img": "https://i.blogs.es/68edba/raclette-portada/840_560.jpg"
    },
    {
        "pregunta": "¿Qué tipo de vino se utiliza comúnmente en la preparación del risotto italiano?",
        "respuesta_correcta": "Vino blanco",
        "opciones_respuesta": [
            "Merlot",
            "Pinot Noir",
            "Chardonnay",
            "Vino blanco"
        ], "img": "https://debandera.es/248-large_default/bandera-de-italia.jpg"
    },
    {
        "pregunta": "¿Cuál es el ingrediente principal en la receta del plato tailandés pad thai?",
        "respuesta_correcta": "Fideos de arroz",
        "opciones_respuesta": [
            "Tofu",
            "Arroz",
            "Fideos de arroz",
            "Miso"
        ], "img": "https://media.grandvoyage.com/uploads/2021/09/29/guia-tailandia-bandera.jpg"
    },
    {
        "pregunta": "¿Qué alimento es el componente principal en el plato español gazpacho?",
        "respuesta_correcta": "Tomate",
        "opciones_respuesta": [
            "Tomate",
            "Pepino",
            "Pimiento",
            "Calabaza"
        ], "img": "https://okdiario.com/img/2022/08/04/curiosidades-historicas-sobre-la-bandera-de-espana.jpg"
    },
    {
        "pregunta": "¿Qué ingrediente se usa para hacer el tradicional sushi japonés?",
        "respuesta_correcta": "Arroz",
        "opciones_respuesta": [
            "Arroz",
            "Salmón",
            "Alga nori",
            "Wasabi"
        ], "img": "https://i.blogs.es/cf0aac/49388085238_5dd24012fb_o/450_1000.jpeg"
    },
    {
        "pregunta": "¿Qué componente esencial se utiliza para hacer la salsa de caramelo?",
        "respuesta_correcta": "Azúcar",
        "opciones_respuesta": [
            "Azúcar",
            "Mantequilla",
            "Leche",
            "Miel"
        ], "img": "https://recipesblob.oetker.es/assets/2f3850bb241940fc849df337680f844c/750x910/caramelo-salado.jpg"
    },
    {
        "pregunta": "¿Cuál es el ingrediente principal en la receta del plato italiano 'Caprese'?",
        "respuesta_correcta": "Tomate",
        "opciones_respuesta": [
            "Tomate",
            "Espinaca",
            "Pepino",
            "Zanahoria"
        ], "img": "https://debandera.es/248-large_default/bandera-de-italia.jpg"
    },
    {
        "pregunta": "¿Cuál es el ingrediente principal en el ceviche peruano?",
        "respuesta_correcta": "Pescado",
        "opciones_respuesta": [
            "Camarones",
            "Pescado",
            "Pulpo",
            "Langosta"
        ], "img": "https://debandera.es/301-large_default/bandera-de-peru.jpg"
    },
    {
        "pregunta": "¿Qué tipo de chocolate se considera el más puro debido a su alta concentración de cacao?",
        "respuesta_correcta": "Chocolate amargo",
        "opciones_respuesta": [
            "Chocolate blanco",
            "Chocolate con leche",
            "Chocolate semiamargo",
            "Chocolate amargo"
        ], "img": "https://mejorconsalud.as.com/wp-content/uploads/2014/02/tableta-chocolate-negro-amargo.jpg"
    },
    {
        "pregunta": "¿Qué fruto se utiliza para hacer el postre 'Tiramisú'?",
        "respuesta_correcta": "Café",
        "opciones_respuesta": [
            "Fresas",
            "Plátano",
            "Café",
            "Limón"
        ], "img": "https://missgourmand.com/wp-content/uploads/2016/07/receta-tiramisu-casero.jpg"
    },
    {
        "pregunta": "¿Cuál es el ingrediente principal en la receta del plato mexicano 'Tacos al pastor'?",
        "respuesta_correcta": "Cerdo",
        "opciones_respuesta": [
            "Carne de res",
            "Pollo",
            "Pescado",
            "Cerdo"
        ], "img": "https://www.seriouseats.com/thmb/4kbwN13BlZnZ3EywrtG2AzCKuYs=/1500x0/filters:no_upscale():max_bytes(150000):strip_icc()/20210712-tacos-al-pastor-melissa-hom-seriouseats-37-f72cdd02c9574bceb1eef1c8a23b76ed.jpg"
    },
    {
        "pregunta": "¿Qué tipo de pasta se usa para hacer el plato italiano 'Ravioli'?",
        "respuesta_correcta": "Pasta rellena",
        "opciones_respuesta": [
            "Espaguetis",
            "Penne",
            "Lasaña",
            "Pasta rellena"
        ], "img": "https://debandera.es/248-large_default/bandera-de-italia.jpg"
    },
    {
        "pregunta": "¿Cuál es el nombre del plato típico español que consiste en una sopa fría de tomate, pimiento, ajo y pepino?",
        "respuesta_correcta": "Gazpacho",
        "opciones_respuesta": [
            "Gazpacho",
            "Salmón ahumado",
            "Fideuá",
            "Tortilla española"
        ], "img": "https://okdiario.com/img/2022/08/04/curiosidades-historicas-sobre-la-bandera-de-espana.jpg"
    },
    {
        "pregunta": "¿Qué embutido español se elabora principalmente con carne de cerdo y especias como el pimentón?",
        "respuesta_correcta": "Chorizo",
        "opciones_respuesta": [
            "Chorizo",
            "Salchichón",
            "Jamón serrano",
            "Morcilla"
        ], "img": "https://okdiario.com/img/2022/08/04/curiosidades-historicas-sobre-la-bandera-de-espana.jpg"
    },
    {
        "pregunta": "¿Cuál es el nombre del plato español que consiste en patatas cortadas en rodajas y cocidas con cebolla, huevo?",
        "respuesta_correcta": "Tortilla española",
        "opciones_respuesta": [
            "Paella",
            "Patatas bravas",
            "Tortilla española",
            "Pisto"
        ], "img": "https://okdiario.com/img/2022/08/04/curiosidades-historicas-sobre-la-bandera-de-espana.jpg"
    },
    {
        "pregunta": "¿Qué bebida alcohólica española se produce principalmente en la región de Andalucía y se obtiene de la destilación del vino?",
        "respuesta_correcta": "Jerez",
        "opciones_respuesta": [
            "Ron",
            "Vodka",
            "Vermut",
            "Jerez"
        ], "img": "https://okdiario.com/img/2022/08/04/curiosidades-historicas-sobre-la-bandera-de-espana.jpg"
    },
    {
        "pregunta": "¿Cuál es el nombre del plato típico español que consiste en arroz preparado con tinta de calamar?",
        "respuesta_correcta": "Arroz negro",
        "opciones_respuesta": [
            "Paella",
            "Fideuá",
            "Arroz con leche",
            "Arroz negro"
        ], "img": "https://okdiario.com/img/2022/08/04/curiosidades-historicas-sobre-la-bandera-de-espana.jpg"
    },
    {
        "pregunta": "¿Qué postre español es una especie de natilla gelatinosa con caramelo líquido por encima?",
        "respuesta_correcta": "Flan",
        "opciones_respuesta": [
            "Tarta de Santiago",
            "Crema catalana",
            "Leche frita",
            "Flan"
        ], "img": "https://okdiario.com/img/2022/08/04/curiosidades-historicas-sobre-la-bandera-de-espana.jpg"
    },
    {
        "pregunta": "¿Qué plato español se prepara con pan, tomate, aceite de oliva y ajo?",
        "respuesta_correcta": "Pan tumaca",
        "opciones_respuesta": [
            "Croquetas",
            "Gazpacho",
            "Pulpo a la gallega",
            "Pan tumaca"
        ], "img": "https://okdiario.com/img/2022/08/04/curiosidades-historicas-sobre-la-bandera-de-espana.jpg"
    },
    {
        "pregunta": "¿Qué embutido español se hace con carne picada, generalmente de cerdo, adobada con especias como la pimienta?",
        "respuesta_correcta": "Salchichon",
        "opciones_respuesta": [
            "Chorizo",
            "Salchichon",
            "Pavo",
            "Jamón serrano"
        ], "img": "https://okdiario.com/img/2022/08/04/curiosidades-historicas-sobre-la-bandera-de-espana.jpg"
    },
    {
        "pregunta": "¿Qué plato típico de la cocina española se hace con garbanzos, chorizo y otros ingredientes?",
        "respuesta_correcta": "Cocido madrileño",
        "opciones_respuesta": [
            "Fabada asturiana",
            "Cocido madrileño",
            "Bacalao al pil pil",
            "Caldereta de langosta"
        ], "img": "https://okdiario.com/img/2022/08/04/curiosidades-historicas-sobre-la-bandera-de-espana.jpg"
    },
    {
        "pregunta": "¿Qué queso es característico de la región de Galicia en España?",
        "respuesta_correcta": "Queso Tetilla",
        "opciones_respuesta": [
            "Queso Manchego",
            "Queso Tetilla",
            "Queso Cabrales",
            "Queso Idiazábal"
        ], "img": "https://elements-video-cover-images-0.imgix.net/files/236378363/preview.jpg?auto=compress%2Cformat&h=394&w=700&fit=min&s=5a0728d7136bf445d0d415c92447293c"
    },
    {
        "pregunta": "¿Cuál es el plato típico de Valencia que lleva arroz, azafrán y diferentes ingredientes como mariscos, pollo y conejo?",
        "respuesta_correcta": "Paella",
        "opciones_respuesta": [
            "Fabada",
            "Paella",
            "Gazpacho",
            "Escudella"
        ], "img": "https://img.freepik.com/fotos-premium/bandera-espana-ciudad-valencia-telon-fondo-cielo-azul-claro_299599-451.jpg"
    },
    {
        "pregunta": "¿Qué plato típico español lleva pan, chorizo, panceta, alubias y otros ingredientes?",
        "respuesta_correcta": "Migas",
        "opciones_respuesta": [
            "Migas",
            "Fideuà",
            "Pisto",
            "Pincho"
        ], "img": "https://okdiario.com/img/2022/08/04/curiosidades-historicas-sobre-la-bandera-de-espana.jpg"
    },
    {
        "pregunta": "¿Qué bebida española se obtiene al mezclar vino tinto con refresco de limón o naranja?",
        "respuesta_correcta": "Tinto de verano",
        "opciones_respuesta": [
            "Tinto de verano",
            "Vermout",
            "Calimocho",
            "Rebujito"
        ], "img": "https://okdiario.com/img/2022/08/04/curiosidades-historicas-sobre-la-bandera-de-espana.jpg"
    },
    {
        "pregunta": "¿Qué tipo de embutido es típico de la región de Cataluña?",
        "respuesta_correcta": "Fuet",
        "opciones_respuesta": [
            "Chorizo",
            "Morcilla",
            "Fuet",
            "Salchichón"
        ], "img": "https://fotografias.antena3.com/clipping/cmsimages02/2022/08/24/52E2E983-DC61-4A46-A00A-597A73C30480/bandera-estelada_98.jpg?crop=4263,2398,x0,y603&width=1900&height=1069&optimize=low&format=webply"
    },
    {
        "pregunta": "¿Qué ingrediente se usa para hacer la salsa alioli?",
        "respuesta_correcta": "Ajo y aceite de oliva",
        "opciones_respuesta": [
            "Ajo y aceite de oliva",
            "Tomate y pimientos",
            "Cebolla y vinagre",
            "Limón y hierbas"
        ], "img": "https://imag.bonviveur.com/presentacion-final-de-la-salsa-alioli-tradicional.jpg"
    },
    {
        "pregunta": "¿Qué tipo de queso es originario de la región de Extremadura?",
        "respuesta_correcta": "Torta del Casar",
        "opciones_respuesta": [
            "Cabrales",
            "Manchego",
            "Torta del Casar",
            "Idiazábal"
        ], "img": "https://imag.bonviveur.com/queso-torta-del-casar-con-la-tapa-abierta.jpg"
    },
    {
        "pregunta": "Cuál es el dulce típico de la Navidad en España hecho con almendras, azúcar y clara de huevo?",
        "respuesta_correcta": "Mazapán",
        "opciones_respuesta": [
            "Polvorones",
            "Mazapán",
            "Roscón de Reyes",
            "Panellets"
        ], "img": "https://fotografias.larazon.es/clipping/cmsimages02/2023/11/08/261FCB39-7942-46E7-9EB5-429F43BC52EF/personas-que-adelantan-navidad-son-mas-felices-segun-estudio_70.jpg?crop=1600,900,x0,y0&width=480&height=270&optimize=low&format=webply"
    },
    {
        "pregunta": "Qué bebida es conocida por su origen en la región de Asturias y se produce a partir de manzanas fermentadas?",
        "respuesta_correcta": "Sidra",
        "opciones_respuesta": [
            "Cava",
            "Sidra",
            "Vermut",
            "Orujo"
        ], "img": "https://s1.ppllstatics.com/elcomercio/www/multimedia/202006/02/media/cortadas/bandera-asturias-historia-kKEI-U1103847865650JF-1248x770@El%20Comercio.JPG"
    },
    {
        "pregunta": "Qué postre típico de la región de Asturias se hace con una masa de hojaldre rellena de crema pastelera?",
        "respuesta_correcta": "Casadielles",
        "opciones_respuesta": [
            "Tarta de la abuela",
            "Arroz con leche",
            "Casadielles",
            "Milhojas"
        ], "img": "https://s1.ppllstatics.com/elcomercio/www/multimedia/202006/02/media/cortadas/bandera-asturias-historia-kKEI-U1103847865650JF-1248x770@El%20Comercio.JPG"
    },
    {
        "pregunta": "Qué postre se hace en la región de Galicia con almendras, azúcar, huevo y limón?",
        "respuesta_correcta": "Tarta de Santiago",
        "opciones_respuesta": [
            "Leche frita",
            "Tarta de Santiago",
            "Crema catalana",
            "Cuajada"
        ], "img": "https://www.cucute.com/blog/wp-content/uploads/2020/06/tarta-de-santiago-3-500x500.jpg"
    },
    {
        "pregunta": "Cuál es el plato típico de Cataluña que consiste en una salsa de tomate con almendras, avellanas, ajo y ñora?",
        "respuesta_correcta": "Romesco",
        "opciones_respuesta": [
            "Escudella i carn d'olla",
            "Fideuà",
            "Romesco",
            "Esqueixada"
        ], "img": "https://fotografias.antena3.com/clipping/cmsimages02/2022/08/24/52E2E983-DC61-4A46-A00A-597A73C30480/bandera-estelada_98.jpg?crop=4263,2398,x0,y603&width=1900&height=1069&optimize=low&format=webply"
    },
    {
        "pregunta": "Qué dulce típico de Cataluña se hace con masa de hojaldre y crema pastelera?",
        "respuesta_correcta": "Xuixo",
        "opciones_respuesta": [
            "Panellets",
            "Crema catalana",
            "Ensaimada",
            "Xuixo"
        ], "img": "https://images.gestionaweb.cat/1957/img-1280-720/1582908332725-photo-2020-02-28-17-31-04-copia-1862346-2-2.jpg"
    },
    {
        "pregunta": "Cuál es el embutido característico de Cataluña hecho con carne de cerdo, pimienta y especias?",
        "respuesta_correcta": "Butifarra",
        "opciones_respuesta": [
            "Butifarra",
            "Fuet",
            "Botifarra",
            "Llonganissa"
        ], "img": "https://fotografias.antena3.com/clipping/cmsimages02/2022/08/24/52E2E983-DC61-4A46-A00A-597A73C30480/bandera-estelada_98.jpg?crop=4263,2398,x0,y603&width=1900&height=1069&optimize=low&format=webply"
    },
    {
        "pregunta": "Qué plato típico de Cataluña se elabora con patatas, cebolla, huevos y a menudo incluye diferentes ingredientes como chorizo o butifarra?",
        "respuesta_correcta": "Trinxat",
        "opciones_respuesta": [
            "Escudella",
            "Fideuà",
            "Tarta de Santiago",
            "Trinxat"
        ], "img": "https://fotografias.antena3.com/clipping/cmsimages02/2022/08/24/52E2E983-DC61-4A46-A00A-597A73C30480/bandera-estelada_98.jpg?crop=4263,2398,x0,y603&width=1900&height=1069&optimize=low&format=webply"
    },
    {
        "pregunta": "¿Cuál es el postre tradicional de Cataluña hecho con almendras, azúcar, huevo y ralladura de limón?",
        "respuesta_correcta": "Panellets",
        "opciones_respuesta": [
            "Panellets",
            "Tarta de Santiago",
            "Crema catalana",
            "Mel i mató"
        ], "img": "https://fotografias.antena3.com/clipping/cmsimages02/2022/08/24/52E2E983-DC61-4A46-A00A-597A73C30480/bandera-estelada_98.jpg?crop=4263,2398,x0,y603&width=1900&height=1069&optimize=low&format=webply"
    },
    {
        "pregunta": "¿Qué plato catalán típico se prepara con pescado fresco, tomate, cebolla, ajo y pimientos?",
        "respuesta_correcta": "Esqueixada",
        "opciones_respuesta": [
            "Esqueixada",
            "Zarzuela",
            "Escalivada",
            "Suquet de peix"
        ], "img": "https://fotografias.antena3.com/clipping/cmsimages02/2022/08/24/52E2E983-DC61-4A46-A00A-597A73C30480/bandera-estelada_98.jpg?crop=4263,2398,x0,y603&width=1900&height=1069&optimize=low&format=webply"
    },
    {
        "pregunta": "¿Cuál es el plato de arroz catalán que se prepara con pescado, mariscos y azafrán?",
        "respuesta_correcta": "Fideuà",
        "opciones_respuesta": [
            "Paella",
            "Fideuà",
            "Arroz negro",
            "Arroz caldoso"
        ], "img": "https://fotografias.antena3.com/clipping/cmsimages02/2022/08/24/52E2E983-DC61-4A46-A00A-597A73C30480/bandera-estelada_98.jpg?crop=4263,2398,x0,y603&width=1900&height=1069&optimize=low&format=webply"
    },
    {
        "pregunta": "¿Qué bebida típica de Cataluña se elabora con vino tinto, frutas y azúcar?",
        "respuesta_correcta": "Clarea",
        "opciones_respuesta": [
            "Sangría",
            "Cava",
            "Horchata",
            "Clarea"
        ], "img": "https://fotografias.antena3.com/clipping/cmsimages02/2022/08/24/52E2E983-DC61-4A46-A00A-597A73C30480/bandera-estelada_98.jpg?crop=4263,2398,x0,y603&width=1900&height=1069&optimize=low&format=webply"
    },
    {
        "pregunta": "¿Qué plato catalán se hace con berenjena, tomate, cebolla, pimiento y aceite de oliva?",
        "respuesta_correcta": "Samfaina",
        "opciones_respuesta": [
            "Samfaina",
            "Escudella",
            "Trinxat",
            "Fideuà"
        ], "img": "https://4.bp.blogspot.com/-Ne7E0lDt-Ow/Ve2r2Kcq3BI/AAAAAAAAFIQ/7LqsVBht5jM/s1600/4.JPG"
    },
    {
        "pregunta": "¿Cuál es el postre catalán que se elabora con requesón y miel?",
        "respuesta_correcta": "Mel i mató",
        "opciones_respuesta": [
            "Mel i mató",
            "Crema catalana",
            "Xuixo",
            "Tarta de Santiago"
        ], "img": "https://www.bautrip.com/images/food/mel-i-mato.jpg"
    },
    {
        "pregunta": "¿Qué postre gallego se prepara con masa de harina, leche, huevos y se rellena con crema o chocolate?",
        "respuesta_correcta": "Filloas",
        "opciones_respuesta": [
            "Filloas",
            "Tarta de Santiago",
            "Bica blanca",
            "Rosquillas"
        ], "img": "https://elements-video-cover-images-0.imgix.net/files/236378363/preview.jpg?auto=compress%2Cformat&h=394&w=700&fit=min&s=5a0728d7136bf445d0d415c92447293c"
    },
    {
        "pregunta": "¿Qué postre típico de Andalucía se hace con rebanadas de pan, leche, huevo y canela?",
        "respuesta_correcta": "Torrijas",
        "opciones_respuesta": [
            "Torrijas",
            "Pestiños",
            "Roscos fritos",
            "Leche frita"
        ], "img": "https://productoslaure.com/wp-content/uploads/2022/04/torrijas-caseras-torrijas-terminadas-plato-receta-e1614077782536.jpg"
    },
    {
        "pregunta": "¿Qué plato andaluz se elabora con trozos de carne de cerdo adobada y frita?",
        "respuesta_correcta": "Chicharrones",
        "opciones_respuesta": [
            "Rabo de toro",
            "Altramuces",
            "Averroes",
            "Chicharrones"
        ], "img": "https://img-global.cpcdn.com/recipes/2b80684fe0e8bb03/680x482cq70/chicharrones-de-cerdo-foto-principal.jpg"
    },
    {
        "pregunta": "¿Cuál es el postre típico de Andalucía hecho con miel, harina, aceite y ajonjolí?",
        "respuesta_correcta": "Pestiños",
        "opciones_respuesta": [
            "Roscos fritos",
            "Pestiños",
            "Torrijas",
            "Leche frita"
        ], "img": "https://s1.abcstatics.com/media/gurmesevilla/2009/07/pestinos.jpg"
    },
    {
        "pregunta": "¿Cuál es el plato andaluz que consiste en un guiso de garbanzos con chorizo, morcilla y otras carnes?",
        "respuesta_correcta": "Potaje",
        "opciones_respuesta": [
            "Gazpacho",
            "Migas",
            "Potaje",
            "Paella"
        ], "img": "https://www.aionsur.com/wp-content/uploads/2019/02/Bandera.jpg"
    },
    {
        "pregunta": "¿Qué plato murciano se hace con calabacín, huevo, cebolla y pimiento?",
        "respuesta_correcta": "Zarangollo",
        "opciones_respuesta": [
            "Caldero",
            "Zarangollo",
            "Michirones",
            "Paparajote"
        ], "img": "https://t1.uc.ltmcdn.com/es/posts/2/7/3/como_hacer_zarangollo_murciano_51372_orig.jpg"
    },
    {
        "pregunta": "¿Cuál es el plato típico murciano que consiste en habas secas con chorizo, panceta y pimentón?",
        "respuesta_correcta": "Michirones",
        "opciones_respuesta": [
            "Caldero",
            "Zarangollo",
            "Michirones",
            "Paparajote"
        ], "img": "https://www.euromarina.com/wp-content/uploads/2014/04/Michirones.jpg"
    },
    {
        "pregunta": "¿Qué postre murciano se elabora con hojas de limonero, masa de harina, huevo y azúcar?",
        "respuesta_correcta": "Paparajote",
        "opciones_respuesta": [
            "Gachas",
            "Paparajote",
            "Pastel de carne",
            "Tocino de cielo"
        ], "img": "https://i.blogs.es/902777/paparajotes/840_560.jpg"
    },
    {
        "pregunta": "¿Qué postre murciano se hace con yema de huevo, azúcar y agua?",
        "respuesta_correcta": "Tocino de cielo",
        "opciones_respuesta": [
            "Gachas",
            "Paparajote",
            "Tocino de cielo",
            "Pastel de carne"
        ], "img": "https://i.blogs.es/9be371/tocino-de-cielo/1366_2000.jpg"
    },
    {
        "pregunta": "¿Qué plato árabe se compone principalmente de garbanzos, especias y hierbas, y se suele servir en forma de croquetas fritas?",
        "respuesta_correcta": "Falafel",
        "opciones_respuesta": [
            "Shawarma",
            "Kebab",
            "Falafel",
            "Hummus"
        ], "img": "https://www.aceitesdeolivadeespana.com/wp-content/uploads/2021/01/receta-falafel.jpg"
    },
    {
        "pregunta": "¿Cuál es el plato árabe compuesto por trigo bulgur, perejil, menta, tomate y pepino?",
        "respuesta_correcta": "Tabbouleh",
        "opciones_respuesta": [
            "Tabbouleh",
            "Shawarma",
            "Kebab",
            "Falafel"
        ], "img": "https://www.tasteofhome.com/wp-content/uploads/2020/10/Tabouleh_EXPS_TOHFM21_250394_E09_22_8b.jpg"
    },
    {
        "pregunta": "¿Qué plato marroquí se caracteriza por ser un pastel de hojaldre relleno de carne de paloma o pollo, almendras y canela?",
        "respuesta_correcta": "Pastela",
        "opciones_respuesta": [
            "Tajine de cordero",
            "Pastela",
            "Harira",
            "Mechoui"
        ], "img": "https://imag.bonviveur.com/pastela-de-pollo-marroqui.jpg"
    },
    {
        "pregunta": "¿Qué plato es una sopa espesa marroquí hecha con tomate, legumbres, carne y especias?",
        "respuesta_correcta": "Harira",
        "opciones_respuesta": [
            "Tajine de cordero",
            "Pastilla",
            "Harira",
            "Mechoui"
        ], "img": "https://www.petitchef.es/imgupl/recipe/harira-sopa-marroqui-para-el-ramadan--453626p702950.jpg"
    },
    {
        "pregunta": "¿Qué plato marroquí es un cordero asado a la parrilla lentamente?",
        "respuesta_correcta": "Mechoui",
        "opciones_respuesta": [
            "Tajine de cordero",
            "Pastilla",
            "Harira",
            "Mechoui"
        ], "img": "https://cdn0.recetasgratis.net/es/posts/9/9/3/mechoui_cordero_asado_a_la_brasa_16399_600_square.jpg"
    },
    {
        "pregunta": "¿Qué plato marroquí es un guiso tradicional con sémola de trigo, verduras y carne de cordero o pollo?",
        "respuesta_correcta": "Couscous",
        "opciones_respuesta": [
            "Tajine de cordero",
            "Pastilla",
            "Harira",
            "Couscous"
        ], "img": "https://www.trevijano.com/wp-content/uploads/Receta-couscous-cacahuetes-miel-caseros-1024x680.jpg"
    },
    {
        "pregunta": "¿Qué plato portugués es una sopa tradicionalmente hecha con puré de patata, col, cebolla y ajo?",
        "respuesta_correcta": "Caldo verde",
        "opciones_respuesta": [
            "Caldo verde",
            "Bacalhau à Brás",
            "Francesinha",
            "Caldereta"
        ], "img": "https://w.forfun.com/fetch/f6/f65d99d1fead6644a8663d1b68bcb502.jpeg"
    },
    {
        "pregunta": "¿Cuál es el plato portugués que consiste en filetes de ternera rellenos de jamón y salchichas, cubiertos con queso y salsa?",
        "respuesta_correcta": "Francesinha",
        "opciones_respuesta": [
            "Ternera en salsa de perejil",
            "Bacalhau e ternera à Brás",
            "Francesinha",
            "Filetes rusos du obrador"
        ], "img": "https://imag.bonviveur.com/foto-del-interior-de-francesinha.jpg  "
    },
    {
        "pregunta": "¿Qué postre portugués son pequeños pasteles de crema y hojaldre, espolvoreados con azúcar glas?",
        "respuesta_correcta": "Pastéis de nata",
        "opciones_respuesta": [
            "Trozos de san andrés",
            "Tocino de cielo",
            "Francesinha",
            "Pastéis de nata"
        ], "img": "https://www.livingtours.com/public/blog/posts/20200123161347-reQkxvU6.jpg    "
    },
    {
        "pregunta": "¿Qué plato portugués es una sopa de pescado con tomate, cebolla y azafrán?",
        "respuesta_correcta": "Sopa de peixe",
        "opciones_respuesta": [
            "Caldo verde",
            "Bacalhau à Brás",
            "Francesinha",
            "Sopa de peixe"
        ], "img": "https://assets.tmecosys.com/image/upload/t_web767x639/img/recipe/ras/Assets/C2E5995F-4034-4E06-8AE8-DA09CF6BD6C7/Derivates/D08F5407-B99C-405A-9700-382F185C1A99.jpg"
    },
    {
        "pregunta": "¿Cuál es el plato típico de Francia compuesto por carne de res estofada en vino tinto con verduras?",
        "respuesta_correcta": "Coq au vin",
        "opciones_respuesta": [
            "Coq au vin",
            "Ratatouille",
            "Bouillabaisse",
            "Cassoulet"
        ], "img": "https://images.immediate.co.uk/production/volatile/sites/30/2012/01/coq-au-vin-3740fe3.jpg?quality=90&resize=556,505"
    },
    {
        "pregunta": "¿Qué postre francés es una masa hojaldrada con crema pastelera?",
        "respuesta_correcta": "Millefeuille",
        "opciones_respuesta": [
            "Éclair",
            "Tarte Tatin",
            "Macaron",
            "Millefeuille"
        ], "img": "https://files.meilleurduchef.com/mdc/photo/recipe/vanilla-millefeuille/vanilla-millefeuille-640.jpg"
    },
    {
        "pregunta": "¿Cuál es el plato francés que consiste en un guiso de verduras como berenjena, tomate, calabacín y pimientos?",
        "respuesta_correcta": "Ratatouille",
        "opciones_respuesta": [
            "Coq au vin",
            "Ratatouille",
            "Bouillabaisse",
            "Cassoulet"
        ], "img": "https://imag.bonviveur.com/ratatouille-recien-horneada.jpg"
    },
    {
        "pregunta": "¿Qué plato francés es un guiso de pescado y mariscos originario de Marsella?",
        "respuesta_correcta": "Bouillabaisse",
        "opciones_respuesta": [
            "Coq au vin",
            "Ratatouille",
            "Bouillabaisse",
            "Cassoulet"
        ], "img": "https://assets.epicurious.com/photos/61f423f29c9591f7270e22c6/4:3/w_4965,h_3723,c_limit/Bouillabaise_RECIPE_20220125_1776_V1_final.jpg"
    },
    {
        "pregunta": "¿Qué postre francés es un pastel invertido de manzanas caramelizadas?",
        "respuesta_correcta": "Tarte Tatin",
        "opciones_respuesta": [
            "Éclair",
            "Tarte Tatin",
            "Macaron",
            "Millefeuille"
        ], "img": "https://imag.bonviveur.com/tarta-tatin-de-manzana-de-las-hermanas-tatin.jpg"
    },
    {
        "pregunta": "¿Cuál es el plato francés hecho con pato, confit de pato, salchichas, cerdo y frijoles blancos?",
        "respuesta_correcta": "Cassoulet",
        "opciones_respuesta": [
            "Coq au vin",
            "Ratatouille",
            "Bouillabaisse",
            "Cassoulet"
        ], "img": "https://assets.tmecosys.com/image/upload/t_web767x639/img/recipe/ras/Assets/cd3d8dcc03978e07baf030eefe376ada/Derivates/d752898b679fc5502c78826a8adae61d0e10e70c.jpg"
    },
    {
        "pregunta": "¿Qué postre francés es una masa de merengue y almendras con diversos sabores?",
        "respuesta_correcta": "Macaron",
        "opciones_respuesta": [
            "Éclair",
            "Tarte Tatin",
            "Macaron",
            "Millefeuille"
        ], "img": "https://images.hola.com/imagenes/cocina/noticiaslibros/20200529168994/macarons-recetas/0-829-535/macarons-m.jpg"
    },
    {
        "pregunta": "¿Qué plato francés es un pastel relleno de crema o chocolate?",
        "respuesta_correcta": "Éclair",
        "opciones_respuesta": [
            "Éclair",
            "Ratatouille",
            "Macaron",
            "Millefeuille"
        ], "img": "https://imag.bonviveur.com/interior-de-los-eclairs-de-crema-y-chocolate.jpg"
    },
    {
        "pregunta": "¿Qué plato típico francés es un rollo de carne relleno de huevo duro y pepinillos?",
        "respuesta_correcta": "Pâté de campagne",
        "opciones_respuesta": [
            "Quiche Lorraine",
            "Pot-au-feu",
            "Bouillabaisse",
            "Pâté de campagne"
        ], "img": "https://www.allrecipes.com/thmb/cpJtvNHG5pILFQk97_nMr4Wz49I=/1500x0/filters:no_upscale():max_bytes(150000):strip_icc()/4473194-chef-johns-pate-de-campagne-Chef-John-4x3-1-815283726d2d49b5acf7bbf459c7d877.jpg"
    },
    {
        "pregunta": "¿Qué postre francés es un pastel de chocolate con centro líquido?",
        "respuesta_correcta": "Fondant au chocolat",
        "opciones_respuesta": [
            "Clafoutis",
            "Tarte Tatin",
            "Fondant au chocolat",
            "Crème brûlée"
        ], "img": ""
    },
    {
        "pregunta": "¿Qué plato francés es una sopa de cebolla gratinada con queso?",
        "respuesta_correcta": "Soupe à l'oignon",
        "opciones_respuesta": [
            "Soupe au pistou",
            "Vichyssoise",
            "Potage Parmentier",
            "Soupe à l'oignon"
        ], "img": ""
    },
    {
        "pregunta": "¿Qué postre francés es una tarta de frutas sobre una base de crema de almendras?",
        "respuesta_correcta": "Tarte aux fruits",
        "opciones_respuesta": [
            "Clafoutis",
            "Tarte Tatin",
            "Galette des rois",
            "Tarte aux fruits"
        ], "img": ""
    },
    {
        "pregunta": "¿Qué plato típico francés es un guiso de carne con papas, zanahorias y vino tinto?",
        "respuesta_correcta": "Blanquette de veau",
        "opciones_respuesta": [
            "Blanquette de veau",
            "Coq au vin",
            "Cassoulet",
            "Pot-au-feu"
        ], "img": ""
    },
    {
        "pregunta": "¿Qué postre francés es un pastel tradicionalmente elaborado con cerezas?",
        "respuesta_correcta": "Clafoutis",
        "opciones_respuesta": [
            "Clafoutis",
            "Tarte Tatin",
            "Galette des rois",
            "Tarte aux fruits"
        ], "img": ""
    },
    {
        "pregunta": "¿Qué plato francés es un guiso de ternera con verduras y hierbas?",
        "respuesta_correcta": "Pot-au-feu",
        "opciones_respuesta": [
            "Blanquette de veau",
            "Coq au vin",
            "Cassoulet",
            "Pot-au-feu"
        ], "img": ""
    },
    {
        "pregunta": "¿Qué plato francés es un guiso de alubias blancas con embutidos y carne de cerdo?",
        "respuesta_correcta": "Cassoulet",
        "opciones_respuesta": [
            "Blanquette de veau",
            "Coq au vin",
            "Cassoulet",
            "Pot-au-feu"
        ], "img": ""
    },
    {
        "pregunta": "¿Qué postre francés es un pastel de hojaldre relleno de almendra y servido el Día de Reyes?",
        "respuesta_correcta": "Galette des rois",
        "opciones_respuesta": [
            "Clafoutis",
            "Tarte Tatin",
            "Galette des rois",
            "Tarte aux fruits"
        ], "img": ""
    },
    {
        "pregunta": "¿Qué plato francés es una mezcla de carne picada con hierbas, envuelta en hojaldre y horneada?",
        "respuesta_correcta": "Pâté en croûte",
        "opciones_respuesta": [
            "Quiche Lorraine",
            "Bœuf bourguignon",
            "Coq au vin",
            "Pâté en croûte"
        ], "img": ""
    },
    {
        "pregunta": "¿Qué postre francés es un bizcocho esponjoso con forma de anillo?",
        "respuesta_correcta": "Savarin",
        "opciones_respuesta": [
            "Madeleine",
            "Financier",
            "Savarin",
            "Brioche"
        ], "img": ""
    },
    {
        "pregunta": "¿Qué plato típico de la región de Normandía es una cazuela de mariscos con una salsa cremosa de ajo y vino blanco?",
        "respuesta_correcta": "Matelote",
        "opciones_respuesta": [
            "Bouillabaisse",
            "Coquilles Saint-Jacques",
            "Moules Marinière",
            "Matelote"
        ], "img": ""
    },
    {
        "pregunta": "¿Qué plato francés es un estofado de carne de ternera con cebollas y vino tinto, cubierto con una masa de hojaldre?",
        "respuesta_correcta": "Bœuf en daube",
        "opciones_respuesta": [
            "Bœuf en daube",
            "Coq au vin",
            "Cassoulet",
            "Beef Wellington"
        ], "img": ""
    },
    {
        "pregunta": "¿Qué postre francés es una masa de choux rellena de crema batida o natillas?",
        "respuesta_correcta": "Profiteroles",
        "opciones_respuesta": [
            "Profiteroles",
            "Millefeuille",
            "Éclair",
            "Crêpe suzette"
        ], "img": ""
    },
    {
        "pregunta": "¿Qué plato francés es un estofado de carne de cordero con verduras y hierbas provenzales?",
        "respuesta_correcta": "Navarin d'agneau",
        "opciones_respuesta": [
            "Navarin d'agneau",
            "Blanquette de veau",
            "Coq au vin",
            "Bœuf bourguignon"
        ], "img": ""
    },
    {
        "pregunta": "¿Qué postre francés es una torta de frutas de la región de Alsacia con masa de levadura y crema pastelera?",
        "respuesta_correcta": "Kouglof",
        "opciones_respuesta": [
            "Tarte Tatin",
            "Clafoutis",
            "Tarte Flambée",
            "Kouglof"
        ], "img": ""
    },
    {
        "pregunta": "¿Qué plato típico de la región de Alsacia es una tarta flan salada con crema, huevos y tocino?",
        "respuesta_correcta": "Quiche Lorraine",
        "opciones_respuesta": [
            "Quiche Lorraine",
            "Ratatouille",
            "Bouillabaisse",
            "Cassoulet"
        ], "img": ""
    },
    {
        "pregunta": "¿Qué postre francés es una masa de hojaldre rellena de crema de almendra y glaseada?",
        "respuesta_correcta": "Religieuse",
        "opciones_respuesta": [
            "Millefeuille",
            "Éclair",
            "Religieuse",
            "Tarte aux fraises"
        ], "img": ""
    },
    {
        "pregunta": "¿Qué plato francés es un guiso de pollo cocido con champiñones, cebolla, vino blanco y crema?",
        "respuesta_correcta": "Blanquette de veau",
        "opciones_respuesta": [
            "Coq au vin",
            "Blanquette de veau",
            "Bouillabaisse",
            "Ratatouille"
        ], "img": ""
    },
    {
        "pregunta": "¿Qué postre francés es una masa de hojaldre rellena de crema pastelera y chocolate?",
        "respuesta_correcta": "Tarte au chocolat",
        "opciones_respuesta": [
            "Religieuse",
            "Éclair",
            "Millefeuille",
            "Tarte au chocolat"
        ], "img": ""
    },
    {
        "pregunta": "¿Qué plato francés es un pastel tradicional de carne picada con capas de puré de patatas?",
        "respuesta_correcta": "Hachis Parmentier",
        "opciones_respuesta": [
            "Quiche Lorraine",
            "Parmentier",
            "Hachis Parmentier",
            "Ratatouille"
        ], "img": ""
    },
    {
        "pregunta": "¿Qué plato típico francés es una sopa fría hecha de pepino, yogur y hierbas?",
        "respuesta_correcta": "Soupe au pistou",
        "opciones_respuesta": [
            "Vichyssoise",
            "Soupe au pistou",
            "Soupe à l'oignon",
            "Soupe de poisson"
        ], "img": ""
    },
    {
        "pregunta": "¿Qué postre francés es un bizcocho esponjoso en forma de concha?",
        "respuesta_correcta": "Madeleine",
        "opciones_respuesta": [
            "Madeleine",
            "Financier",
            "Cannele",
            "Savarin"
        ], "img": ""
    },
    {
        "pregunta": "¿Qué plato inglés es un estofado de carne de res con cebollas, zanahorias y patatas?",
        "respuesta_correcta": "Roast Beef",
        "opciones_respuesta": [
            "Shepherd's Pie",
            "Fish and Chips",
            "Beef Wellington",
            "Roast Beef"
        ], "img": ""
    },
    {
        "pregunta": "¿Qué plato inglés es un pastel de carne picada cubierto de puré de patatas?",
        "respuesta_correcta": "Shepherd's Pie",
        "opciones_respuesta": [
            "Shepherd's Pie",
            "Fish and Chips",
            "Beef Wellington",
            "Bangers and Mash"
        ], "img": ""
    },
    {
        "pregunta": "¿Qué plato inglés es un plato de pescado frito y patatas fritas?",
        "respuesta_correcta": "Fish and Chips",
        "opciones_respuesta": [
            "Shepherd's Pie",
            "Fish and Chips",
            "Beef Wellington",
            "Bangers and Mash"
        ], "img": ""
    },
    {
        "pregunta": "¿Qué postre inglés es una tarta con dátiles y una salsa de caramelo?",
        "respuesta_correcta": "Sticky Toffee Pudding",
        "opciones_respuesta": [
            "Trifle",
            "Sticky Toffee Pudding",
            "Bread and Butter Pudding",
            "Christmas Pudding"
        ], "img": ""
    },
    {
        "pregunta": "¿Qué plato alemán es una salchicha típica, generalmente servida con mostaza y pan?",
        "respuesta_correcta": "Bratwurst",
        "opciones_respuesta": [
            "Bratwurst",
            "Sauerkraut",
            "Schnitzel",
            "Currywurst"
        ], "img": ""
    },
    {
        "pregunta": "¿Qué postre alemán es un pastel de chocolate con capas de crema batida y cerezas?",
        "respuesta_correcta": "Black Forest Cake",
        "opciones_respuesta": [
            "Black Forest Cake",
            "Apfelstrudel",
            "Linzer Torte",
            "Sachertorte"
        ], "img": ""
    },
    {
        "pregunta": "¿Cuál es el plato alemán que consiste en salchichas bañadas en salsa de curry?",
        "respuesta_correcta": "Currywurst",
        "opciones_respuesta": [
            "Bratwurst",
            "Sauerkraut",
            "Schnitzel",
            "Currywurst"
        ], "img": ""
    },
    {
        "pregunta": "¿Cuál es el plato alemán que consiste en col fermentada?",
        "respuesta_correcta": "Sauerkraut",
        "opciones_respuesta": [
            "Bratwurst",
            "Sauerkraut",
            "Schnitzel",
            "Currywurst"
        ], "img": ""
    },
    {
        "pregunta": "¿Cuál es el postre turco hecho con capas de masa filo, nueces trituradas y almíbar?",
        "respuesta_correcta": "Baklava",
        "opciones_respuesta": [
            "Baklava",
            "Kunefe",
            "Lokum",
            "Sütlaç"
        ], "img": ""
    },
    {
        "pregunta": "¿Qué plato turco es una pizza tradicional con carne picada y especias?",
        "respuesta_correcta": "Lahmacun",
        "opciones_respuesta": [
            "Kebab",
            "Baklava",
            "Dolma",
            "Lahmacun"
        ], "img": ""
    },
    {
        "pregunta": "¿Qué plato chino es un método de cocción donde se cocinan varios ingredientes en un caldo hirviendo en la mesa?",
        "respuesta_correcta": "Hot Pot",
        "opciones_respuesta": [
            "Peking Duck",
            "Chow Mein",
            "Hot Pot",
            "Wonton Soup"
        ], "img": ""
    },
    {
        "pregunta": "¿Cuál es el nombre del plato chino de albóndigas envueltas en masa y cocidas al vapor o hervidas?",
        "respuesta_correcta": "Dumplings",
        "opciones_respuesta": [
            "Dumplings",
            "Wonton",
            "Peking duck",
            "Xiao Long Bao"
        ], "img": ""
    },
    {
        "pregunta": "¿Qué plato chino es una mezcla de verduras salteadas con salsa de ostras y pollo o carne?",
        "respuesta_correcta": "Chop Suey",
        "opciones_respuesta": [
            "Chop Suey",
            "Moo Shu",
            "Chow Mein",
            "Ternera agridulce"
        ], "img": ""
    },
    {
        "pregunta": "¿Cuál es el nombre del plato tailandés que consiste en fideos de arroz salteados con huevo, tofu, gambas y cacahuetes?",
        "respuesta_correcta": "Pad Thai",
        "opciones_respuesta": [
            "Tom Kha Gai",
            "Som Tam",
            "Pad See Ew",
            "Pad Thai"
        ], "img": ""
    },
    {
        "pregunta": "¿Cuál es la pasta italiana en forma de tubo largo y hueco, perfecta para salsas espesas y condimentadas?",
        "respuesta_correcta": "Penne",
        "opciones_respuesta": [
            "Penne",
            "Spaghetti",
            "Farfalle",
            "Fusilli"
        ], "img": ""
    },
    {
        "pregunta": "¿Cuál es el plato italiano que consiste en capas de pasta, salsa de tomate, queso y carne molida?",
        "respuesta_correcta": "Lasagna",
        "opciones_respuesta": [
            "Pizza",
            "Lasagna",
            "Carbonara",
            "Risotto"
        ], "img": ""
    },
    {
        "pregunta": "¿Qué tipo de pizza se compone de tomate, mozzarella y albahaca fresca?",
        "respuesta_correcta": "Pizza Margherita",
        "opciones_respuesta": [
            "Pizza Margherita",
            "Pizza Marinara",
            "Pizza Diavola",
            "Pizza Quattro Stagioni"
        ], "img": ""
    },
    {
        "pregunta": "¿Cuál es el plato italiano que consiste en una pasta en forma de pequeñas piezas rellenas de carne, queso o verduras?",
        "respuesta_correcta": "Ravioli",
        "opciones_respuesta": [
            "Lasagna",
            "Risotto",
            "Cannelloni",
            "Ravioli"
        ], "img": ""
    },
    {
        "pregunta": "¿Qué tipo de pizza es una pizza sin salsa de tomate, solo aceite de oliva, ajo y orégano?",
        "respuesta_correcta": "Pizza Bianca",
        "opciones_respuesta": [
            "Pizza Margherita",
            "Pizza Marinara",
            "Pizza Diavola",
            "Pizza Bianca"
        ], "img": ""
    },
    {
        "pregunta": "¿Cuál es el plato italiano que consiste en una pasta en forma de pequeñas conchas, perfecta para retener salsas?",
        "respuesta_correcta": "Conchiglie",
        "opciones_respuesta": [
            "Penne",
            "Spaghetti",
            "Farfalle",
            "Conchiglie"
        ], "img": ""
    },
    {
        "pregunta": "¿Qué tipo de pizza lleva tomate, mozzarella, jamón, alcachofas, aceitunas y champiñones?",
        "respuesta_correcta": "Pizza Quattro Stagioni",
        "opciones_respuesta": [
            "Pizza Margherita",
            "Pizza Marinara",
            "Pizza Diavola",
            "Pizza Quattro Stagioni"
        ], "img": ""
    },
    {
        "pregunta": "¿Cuál es el plato italiano que consiste en una masa frita rellena de crema de ricotta y chocolate?",
        "respuesta_correcta": "Cannoli",
        "opciones_respuesta": [
            "Cannoli",
            "Tiramisú",
            "Panna Cotta",
            "Zabaione"
        ], "img": ""
    },
    {
        "pregunta": "¿Qué tipo de pasta italiana es corta y con forma de espiral o hélice?",
        "respuesta_correcta": "Fusilli",
        "opciones_respuesta": [
            "Penne",
            "Spaghetti",
            "Farfalle",
            "Fusilli"
        ], "img": ""
    },
    {
        "pregunta": "¿Cuál es el plato italiano que consiste en capas de berenjenas fritas, salsa de tomate y queso, gratinado al horno?",
        "respuesta_correcta": "Melanzane alla Parmigiana",
        "opciones_respuesta": [
            "Lasagna",
            "Melanzane alla Parmigiana",
            "Cannelloni",
            "Focaccia"
        ], "img": ""
    },
    {
        "pregunta": "¿Qué tipo de pizza tiene solo tomate, ajo, orégano y aceite de oliva?",
        "respuesta_correcta": "Pizza Marinara",
        "opciones_respuesta": [
            "Pizza Margherita",
            "Pizza Marinara",
            "Pizza Diavola",
            "Pizza Quattro Stagioni"
        ], "img": ""
    },
    {
        "pregunta": "¿Cuál es el plato italiano que consiste en finas rebanadas de carne cruda aliñada con aceite de oliva, limón y parmesano?",
        "respuesta_correcta": "Carpaccio",
        "opciones_respuesta": [
            "Carpaccio",
            "Bruschetta",
            "Caprese",
            "Prosciutto"
        ], "img": ""
    },
    {
        "pregunta": "¿Qué tipo de pasta italiana es parecida a los espaguetis pero más gruesa y hueca por dentro?",
        "respuesta_correcta": "Rigatoni",
        "opciones_respuesta": [
            "Penne",
            "Spaghetti",
            "Rigatoni",
            "Linguine"
        ], "img": ""
    },
    {
        "pregunta": "¿Cuál es el plato italiano que consiste en bolitas de arroz rellenas con queso y fritas?",
        "respuesta_correcta": "Arancini",
        "opciones_respuesta": [
            "Cannoli",
            "Arancini",
            "Tiramisú",
            "Panna Cotta"
        ], "img": ""
    },
    {
        "pregunta": "¿Qué tipo de pasta italiana es plana y ancha, ideal para salsas más cremosas?",
        "respuesta_correcta": "Tagliatelle",
        "opciones_respuesta": [
            "Penne",
            "Spaghetti",
            "Tagliatelle",
            "Fusilli"
        ], "img": ""
    },
    {
        "pregunta": "¿Cuál es el plato italiano que consiste en láminas de pasta rellenas de carne, queso o verduras y cocidas al horno con salsa?",
        "respuesta_correcta": "Cannelloni",
        "opciones_respuesta": [
            "Lasagna",
            "Risotto",
            "Cannelloni",
            "Gnocchi"
        ], "img": ""
    },
    {
        "pregunta": "¿Qué tipo de pizza tiene tomate, mozzarella, anchoas y aceitunas negras?",
        "respuesta_correcta": "Pizza Siciliana",
        "opciones_respuesta": [
            "Pizza Margherita",
            "Pizza Marinara",
            "Pizza Diavola",
            "Pizza Siciliana"
        ], "img": ""
    },
    {
        "pregunta": "¿Cuál es el plato italiano que consiste en una tarta con base de galleta y crema de mascarpone?",
        "respuesta_correcta": "Tiramisú",
        "opciones_respuesta": [
            "Cannoli",
            "Arancini",
            "Tiramisú",
            "Cheesecake"
        ], "img": ""
    },
    {
        "pregunta": "¿Qué tipo de pasta italiana es similar a los espaguetis, pero más delgada y larga?",
        "respuesta_correcta": "Linguine",
        "opciones_respuesta": [
            "Penne",
            "Fettuccine",
            "Linguine",
            "Rigatoni"
        ], "img": ""
    },
    {
        "pregunta": "¿Cuál es el nombre del plato mexicano que consiste en tortillas de maíz rellenas de queso y otros ingredientes, dobladas y cocinadas?",
        "respuesta_correcta": "Quesadillas",
        "opciones_respuesta": [
            "Enchiladas",
            "Tamales",
            "Quesadillas",
            "Gorditas"
        ], "img": ""
    },
    {
        "pregunta": "¿Cuál es el nombre del plato mexicano que consiste en carne de cerdo marinada y cocida lentamente en adobo?",
        "respuesta_correcta": "Cochinita Pibil",
        "opciones_respuesta": [
            "Tacos al Pastor",
            "Birria",
            "Cochinita Pibil",
            "Mole Poblano"
        ], "img": ""
    },
    {
        "pregunta": "¿Cuál es el plato estadounidense que consiste en una mezcla de pasta y queso, tradicionalmente con cheddar, horneada hasta gratinar?",
        "respuesta_correcta": "Mac and Cheese",
        "opciones_respuesta": [
            "Hot Dog",
            "Hamburger",
            "Meatloaf",
            "Mac and Cheese"
        ], "img": ""
    },
    {
        "pregunta": "¿Qué plato típico de desayuno estadounidense son panqueques apilados con mantequilla y jarabe de arce?",
        "respuesta_correcta": "Pancakes",
        "opciones_respuesta": [
            "Pancakes",
            "Waffles",
            "French Toast",
            "Bagels"
        ], "img": ""
    },
    {
        "pregunta": "¿Cuál es el plato estadounidense que consiste en trozos de pollo rebozados y fritos, a menudo servidos con salsa picante?",
        "respuesta_correcta": "Fried Chicken",
        "opciones_respuesta": [
            "Fried Chicken",
            "BBQ Ribs",
            "Clam Chowder",
            "Lobster Roll"
        ], "img": ""
    },
    {
        "pregunta": "¿Qué plato estadounidense es una sopa espesa hecha de almejas, patatas, cebolla y tocino?",
        "respuesta_correcta": "Clam Chowder",
        "opciones_respuesta": [
            "Fried Chicken",
            "BBQ Ribs",
            "Clam Chowder",
            "Lobster Roll"
        ], "img": ""
    },
    {
        "pregunta": "¿Cuál es el plato típico del sur de Estados Unidos que consiste en costillas de cerdo cocidas lentamente y glaseadas con salsa barbacoa?",
        "respuesta_correcta": "BBQ Ribs",
        "opciones_respuesta": [
            "Fried Chicken",
            "BBQ Ribs",
            "Clam Chowder",
            "Lobster Roll"
        ], "img": ""
    },
    {
        "pregunta": "¿Cuál es el plato estadounidense que consiste en un sándwich de langosta servido en un panecillo tostado con mantequilla?",
        "respuesta_correcta": "Lobster Roll",
        "opciones_respuesta": [
            "Fried Chicken",
            "BBQ Ribs",
            "Clam Chowder",
            "Lobster Roll"
        ], "img": ""
    },
    {
        "pregunta": "¿Cuál es el plato típico de desayuno estadounidense que consiste en rebanadas de pan sumergidas en huevo batido y luego fritas?",
        "respuesta_correcta": "French Toast",
        "opciones_respuesta": [
            "Pancakes",
            "Waffles",
            "French Toast",
            "Bagels"
        ], "img": ""
    }
]